{
    "$schema": "http://apidocs.iqrfsdk.org/iqrfgd2-schemas/com.iqrftech.self-desc/schema/jsonschema/1-0-0#",
    "self": {
        "vendor": "com.iqrftech.self-desc",
        "name": "schema__iqrf__JsonDpaApiRaw",
        "format": "jsonschema",
        "version": "1-0-0"
    },
    "type": "object",
    "properties": {
        "component": {
            "type": "string",
            "description": "Name of component.",
            "enum": [
                "iqrf::JsonDpaApiRaw"
            ]
        },
        "instance": {
            "type": "string",
            "description": "Recomended iqrf::JsonDpaApiRaw-(id)",
            "default": "iqrf::JsonDpaApiRaw-1"
        },
        "asyncDpaMessage": {
            "type": "boolean",
            "description": "...",
            "default": true
        },
        "RequiredInterfaces": {
            "type": "array",
            "description": "Array of required interfaces..",
            "items": {
                "type": "object",
                "properties": {
                    "name": {
                        "type": "string",
                        "default": "iqrf::IMessagingService",
                        "description": "..."
                    },
                    "target": {
                        "type": "object"
                    }
                },
                "required": [
                    "name",
                    "target"
                ]
            }
        }
    },
    "required": [
        "component",
        "instance"
    ]
}