[{"standardID": -1, "name": "Driver Library"}, {"standardID": 0, "name": "Embed: Coordinator"}, {"standardID": 1, "name": "Embed: Node"}, {"standardID": 2, "name": "Embed: OS"}, {"standardID": 3, "name": "Embed: EEPROM"}, {"standardID": 4, "name": "Embed: EEEPROM"}, {"standardID": 5, "name": "Embed: RAM"}, {"standardID": 6, "name": "Embed: Red LED"}, {"standardID": 7, "name": "Embed: Green LED"}, {"standardID": 8, "name": "Embed: SPI"}, {"standardID": 9, "name": "Embed: IO"}, {"standardID": 10, "name": "Embed: Thermometer"}, {"standardID": 11, "name": "Embed: PWM"}, {"standardID": 12, "name": "Embed: UART"}, {"standardID": 13, "name": "Embed: FRC"}, {"standardID": 75, "name": "IQRF: Binary Output"}, {"standardID": 94, "name": "IQRF: Sensor"}, {"standardID": 113, "name": "IQRF: Light"}, {"standardID": 255, "name": "Embed: DPA Exploration"}]