{
  "mType": "iqrfEmbedOs_WriteCfg",
  "data": {
    "msgId": "sint cupidatat esse l",
    "timeout": -7515192,
    "rsp": {
      "nAdr": -7856352,
      "hwpId": 5745016,
      "rCode": 39138860,
      "dpaVal": -27457738
    },
    "raw": {
      "request": "eu eiusmo",
      "requestTs": "est amet aute",
      "confirmation": "sint irure",
      "confirmationTs": "magna ut Ut ullamco cillum",
      "response": "in Duis nisi velit labore",
      "responseTs": "qui ut nisi dolor incididunt"
    },
    "insId": "la",
    "status": 92509131,
    "statusStr": "dolor irure quis sit"
  }
}