{
  "mType": "iqrfSensor_Enumerate",
  "data": {
    "msgId": "aa62798e-75d4-44f6-b3fd-7a484ac97f82",
    "rsp": {
      "nAdr": 1,
      "pNum": 94,
      "pCmd": 190,
      "hwpId": 5122,
      "rCode": 0,
      "dpaVal": 94,
      "result": {
        "sensors": [
          {
            "id": "TEMPERATURE",
            "type": 1,
            "name": "Temperature",
            "shortName": "T",
            "unit": "°C",
            "decimalPlaces": 4,
            "frcs": [
              144,
              224
            ]
          },
          {
            "id": "CO2",
            "type": 2,
            "name": "Carbon dioxide",
            "shortName": "CO2",
            "unit": "ppm",
            "decimalPlaces": 0,
            "frcs": [
              144,
              224
            ]
          },
          {
            "id": "VOC",
            "type": 3,
            "name": "Volatile organic compound",
            "shortName": "VOC",
            "unit": "ppm",
            "decimalPlaces": 0,
            "frcs": [
              144,
              224
            ]
          },
          {
            "id": "RELATIVE_HUMIDITY",
            "type": 128,
            "name": "Relative humidity",
            "shortName": "RH",
            "unit": "%",
            "decimalPlaces": 1,
            "frcs": [
              144
            ]
          },
          {
            "id": "BINARYDATA7",
            "type": 129,
            "name": "Binary data7",
            "shortName": "bin7",
            "unit": "?",
            "decimalPlaces": 0,
            "frcs": [
              16,
              144
            ]
          },
          {
            "id": "DATA_BLOCK",
            "type": 192,
            "name": "Data block",
            "shortName": "datablock",
            "unit": "?",
            "decimalPlaces": 0,
            "frcs": []
          },
          {
            "id": "BINARYDATA30",
            "type": 160,
            "name": "Binary data30",
            "shortName": "bin30",
            "unit": "?",
            "decimalPlaces": 0,
            "frcs": [
              224,
              249
            ]
          }
        ]
      }
    },
    "raw": [
      {
        "request": "01.00.5e.3e.ff.ff",
        "requestTs": "2024-12-03T11:17:51.794+01:00",
        "confirmation": "01.00.5e.3e.ff.ff.ff.5c.01.08.01",
        "confirmationTs": "2024-12-03T11:17:51.832+01:00",
        "response": "01.00.5e.be.02.14.00.5e.01.02.03.80.81.c0.a0",
        "responseTs": "2024-12-03T11:17:52.090+01:00"
      }
    ],
    "insId": "iqrfgd2-default",
    "statusStr": "ok",
    "status": 0
  }
}
